jp_tools/__init__.py
jp_tools/utils.py
jp_tools-0.5.7.dist-info/METADATA
jp_tools-0.5.7.dist-info/WHEEL
jp_tools-0.5.7.dist-info/entry_points.txt
jp_tools-0.5.7.dist-info/licenses/LICENSE
jp_tools-0.5.7.dist-info/RECORD
