Metadata-Version: 2.4
Name: jp_tools
Version: 0.5.7
Summary: A simple download hellper to pull files
Author-email: Alejandro Ouslan <alejandro.ouslan@upr.edu>
License-Expression: GPL-3.0-or-later
License-File: LICENSE
Requires-Python: >=3.10
Requires-Dist: numpy>=2.2.6
Requires-Dist: requests>=2.32.5
Requires-Dist: tqdm>=4.67.1
